stackjoiner/__init__.py
stackjoiner/cf_tag.py
stackjoiner/cli.py
stackjoiner/stackjoiner.py
stackjoiner/yaml_loader.py
stackjoiner/tests/__init__.py
stackjoiner/tests/test_cloud_formation_formating.py
stackjoiner/tests/test_load_nested_template.py
stackjoiner/tests/test_load_template.py
stackjoiner/tests/resources/single_nested_template.yaml
stackjoiner/tests/resources/single_template.yaml
stackjoiner-0.1.5.dist-info/entry_points.txt
stackjoiner-0.1.5.dist-info/LICENSE
stackjoiner-0.1.5.dist-info/WHEEL
stackjoiner-0.1.5.dist-info/METADATA
stackjoiner-0.1.5.dist-info/RECORD
