Metadata-Version: 2.1
Name: stackjoiner
Version: 0.1.5
Summary: An amazing sample package!
Author-email: João Marcos <jmarcosdo@gmail.com>
Classifier: License :: OSI Approved :: MIT License
Requires-Dist: PyYAML==6.0
Project-URL: Home, https://github.com/JaoMarcos/StackJoiner
